{"key_paths": ["log_dir_thesis/csvs/testreward", "log_dir_thesis/csvs/testreward", "log_dir_thesis/csvs/testreward", "log_dir_thesis/csvs/testreward", "log_dir_thesis/csvs/testreward", "log_dir_thesis/csvs/avg_cost", "log_dir_thesis/csvs/avg_cost"], "y_df_labels": ["test/reward", "test/reward", "test/reward", "test/reward", "test/reward", "avg_cost", "avg_cost"], "invert_y": [true, true, true, true, true, false, false], "x_df_label": "Steps", "y_display_label": "average solution length", "x_display_label": "number of samples trained", "run_names": ["run_129__20220501T214922", "run_126__20220429T203838", "run_167__20220501T094242", "run_127__20220501T213709", "run_128__20220429T203856", "run_k37__20220503T151519", "run_k35__20220502T172652"], "line_names": ["DQN", "PG", "SAC", "A2C", "PPO", "PG Kool no baseline", "PG Kool with baseline"], "plot_filename": "tsp_final_trainings_zoom", "legend_title": "Algorithm", "is_reward_plot": true, "y_type": "linear"}